examuploader/__init__.py
examuploader/config.py
examuploader/main.py
examuploader/api/__init__.py
examuploader/api/endpoints/health.py
examuploader/api/endpoints/upload.py
examuploader/models/generic_response.py
examuploader/models/health_check.py
examuploader/models/http_error.py
examuploader/models/upload_data.py
examuploader_sebastian_stigler-0.2.2.dist-info/LICENSE.txt
examuploader_sebastian_stigler-0.2.2.dist-info/METADATA
examuploader_sebastian_stigler-0.2.2.dist-info/WHEEL
examuploader_sebastian_stigler-0.2.2.dist-info/top_level.txt
examuploader_sebastian_stigler-0.2.2.dist-info/RECORD
