Metadata-Version: 2.1
Name: examuploader-sebastian-stigler
Version: 0.2.2
Summary: Web application to upload exam files to by SaveDownloadExam!
Home-page: https://in-stigler.htw-aalen.de/gitea/tools/examuploader
Author: Sebastian Stigler
Author-email: sebastian.stigler@hs-aalen.de
License: MIT
Project-URL: Documentation, https://pyscaffold.org/
Platform: any
Classifier: Development Status :: 4 - Beta
Classifier: Programming Language :: Python
License-File: LICENSE.txt
Requires-Dist: fastapi[all] ==0.103.1
Requires-Dist: pydantic-settings-yaml
Requires-Dist: importlib-metadata ; python_version < "3.8"
Provides-Extra: testing
Requires-Dist: setuptools ; extra == 'testing'
Requires-Dist: pytest ; extra == 'testing'
Requires-Dist: pytest-cov ; extra == 'testing'
